[
  {
    "relationship_type": "affects",
    "source_id": "6ae97bcb-e093-47f9-a15c-b831babb427d",
    "target_id": "sys-001",
    "weight": 1.0,
    "confidence": 0.95
  },
  {
    "relationship_type": "affects",
    "source_id": "6ae97bcb-e093-47f9-a15c-b831babb427d",
    "target_id": "bc-001",
    "weight": 1.0,
    "confidence": 0.95
  },
  {
    "relationship_type": "subject_to",
    "source_id": "6ae97bcb-e093-47f9-a15c-b831babb427d",
    "target_id": "reg-001",
    "weight": 1.0,
    "confidence": 0.95
  },
  {
    "relationship_type": "affects",
    "source_id": "4ebb7cae-ca7d-4ee7-85b9-a9ec10e1baa6",
    "target_id": "sys-001",
    "weight": 1.0,
    "confidence": 0.95
  },
  {
    "relationship_type": "affects",
    "source_id": "4ebb7cae-ca7d-4ee7-85b9-a9ec10e1baa6",
    "target_id": "bc-001",
    "weight": 1.0,
    "confidence": 0.95
  },
  {
    "relationship_type": "subject_to",
    "source_id": "4ebb7cae-ca7d-4ee7-85b9-a9ec10e1baa6",
    "target_id": "reg-001",
    "weight": 1.0,
    "confidence": 0.95
  },
  {
    "relationship_type": "affects",
    "source_id": "dedaee5c-33e9-4f9f-9eb3-9581ace27fdd",
    "target_id": "sys-001",
    "weight": 1.0,
    "confidence": 0.95
  },
  {
    "relationship_type": "affects",
    "source_id": "dedaee5c-33e9-4f9f-9eb3-9581ace27fdd",
    "target_id": "bc-001",
    "weight": 1.0,
    "confidence": 0.95
  },
  {
    "relationship_type": "subject_to",
    "source_id": "dedaee5c-33e9-4f9f-9eb3-9581ace27fdd",
    "target_id": "reg-001",
    "weight": 1.0,
    "confidence": 0.95
  },
  {
    "relationship_type": "affects",
    "source_id": "38ee36c9-d02f-4b08-96b8-6b1b73bd49d3",
    "target_id": "sys-001",
    "weight": 1.0,
    "confidence": 0.95
  }
]