{
  "sub_stage": "6.6",
  "document_metadata": {
    "title": "Coherence Assessment - Overall Technology Estate Integrity Evaluation",
    "target_entity": "Rackspace Technology, Inc.",
    "analysis_date": "2026-02-10"
  },
  "coherence_assessment": "CONTRADICTORY",
  "assessment_rationale": "The technology estate exhibits FUNDAMENTAL CONTRADICTIONS between stated principles and operational reality across eight critical dimensions. The estate is NOT simply 'complex but coherent' or 'fragile but functional' - it is SUSTAINED THROUGH CONTRADICTION, EXCEPTION, AND WORKAROUND. Key findings: (1) CENTRALIZATION VS FEDERATION: Presents as unified global company with single brand, operates as federation of 100+ entities with fragmented systems - NO operational integration despite customer-facing unity. (2) FLEXIBILITY VS LOCK-IN: Markets multi-cloud as customer flexibility, reality is triple lock-in (AWS + Azure + Google simultaneously dependent, ZERO exit feasibility) creating 3X operational burden not optionality. (3) AGNOSTIC VS EMBEDDED: Positions as vendor-agnostic management layer, deeply embedded in platforms (VMware $1,055M revenue hostage to Broadcom 200-300% exploitation, hyperscaler API dependencies) preventing any platform change without business destruction. (4) INTEGRATED VS PARALLEL: Presents Private Cloud + Public Cloud as integrated hybrid portfolio, operates as incompatible parallel stacks (VMware vs hyperscaler, different economics, different teams, zero synergy, cannot repurpose declining Private Cloud assets for growing Public Cloud). (5) GLOBAL VS FRAGMENTED: Markets as global platform with consistent capabilities, operates as jurisdictional silos (FedRAMP isolated, UK Sovereign isolated, China isolated, EU constrained) - each segment is single point of failure with zero cross-jurisdiction redundancy. (6) EXCELLENCE VS BRITTLENESS: Brands on 'Fanatical Support' operational excellence, delivers through manual processes (compliance evidence $3-9M manual effort), brittle integrations (15-25% incidents integration-related), aging platforms (VMware), tribal knowledge, heroic engineer effort compensating for technical debt. (7) SCALE ECONOMIES VS COMPLEXITY COMPOUNDING: Traditional expectation that scale reduces unit costs, Rackspace reality is scale INCREASES complexity (customers × clouds × jurisdictions × certifications = combinatorial explosion) - more revenue creates more operational burden not efficiency, explains negative operating margins despite $2.7B scale. (8) PERMANENCE OF CONTRADICTIONS: None of these contradictions are TRANSITIONAL states awaiting resolution - all are STRUCTURAL and PERMANENT due to: Regulatory mandates (FedRAMP, UK Sovereign, China CSL require fragmentation), Customer dependencies (workloads lock Rackspace to platforms), Vendor power (hyperscalers, Broadcom control terms), Capital constraints ($10-35M discretionary capital insufficient to fund resolutions requiring $50-500M per contradiction), Economic irrationality (fixing contradictions costs more than living with them - exit barriers exceed pain thresholds). ESTATE COHERENCE EVALUATION: (A) INTERNAL LOGIC CONSISTENCY: FAILS - estate operates on contradictory principles (centralized vs federated, flexible vs locked-in, agnostic vs embedded), no unifying architectural vision, exceptions dominate norms. (B) OPERATIONAL SUSTAINABILITY: MARGINAL - estate functions through heroic effort, manual workarounds, vendor tolerance, customer inertia - not through design soundness. Brittleness increasing over time (technical debt compounds, platforms age, complexity grows). (C) STRATEGIC ALIGNMENT: FAILS - positioning (unified, flexible, agnostic, excellent) completely disconnected from operational reality (fragmented, locked-in, embedded, brittle). Marketing promises unsupported by technology reality. (D) CHANGE CAPACITY: NEAR ZERO - eight platforms identified as untouchable (Stage 6.3), vendor dependencies have VERY LOW exit feasibility (Stage 6.4), technical debt permanent (Stage 6.5), contradictions structural - estate is FROZEN, cannot evolve without destroying value. OVERALL: Estate is CONTRADICTORY not coherent - survives through CONTRADICTION MANAGEMENT (accepting incompatible realities, operating multiple truth systems simultaneously, preventing different parts from touching to avoid exposing incompatibility) rather than through coherent design. This is not 'technical debt' or 'legacy burden' (implies fixable) - this is STRUCTURAL INCOHERENCE that is PERMANENT and IRREVERSIBLE within business survival constraints. Estate will persist in contradictory state until external force resolves contradictions (acquisition by entity with capital to rationalize, bankruptcy restructuring enabling radical simplification, or business failure eliminating contradictions through cessation). Orderly contradiction resolution from within business is IMPOSSIBLE - capital insufficient, timeline too long, value destruction too great. Rackspace is OPERATIONALLY TRAPPED in contradictory technology estate that undermines execution, prevents evolution, and creates permanent cost/complexity burden."
}
